Metadata-Version: 1.0
Name: currenpy
Version: 1.0.4
Summary: Python currency management library.
Home-page: https://github.com/theunravelghoul/currenpy
Author: theunravelghoul
Author-email: UNKNOWN
License: MIT
Platform: UNKNOWN
